edea_draw/__init__.py
edea_draw/draw.py
edea_draw/py.typed
edea_draw/pcb/__init__.py
edea_draw/pcb/pcb.py
edea_draw/pcb/utils/__init__.py
edea_draw/pcb/utils/kicad_version.py
edea_draw/pcb/utils/svg.py
edea_draw/schematic/__init__.py
edea_draw/schematic/schematic.py
edea_draw/schematic/shapes.py
edea_draw/schematic/symbol.py
edea_draw/themes/__init__.py
edea_draw/themes/style.py
edea_draw/themes/themes.py
edea_draw/themes/types.py
edea_draw/themes/json/behave_dark.json
edea_draw/themes/json/black_white.json
edea_draw/themes/json/blue_green_dark.json
edea_draw/themes/json/blue_tone.json
edea_draw/themes/json/eagle_dark.json
edea_draw/themes/json/kicad_2020.json
edea_draw/themes/json/kicad_2022.json
edea_draw/themes/json/kicad_classic.json
edea_draw/themes/json/monokai.json
edea_draw/themes/json/nord.json
edea_draw/themes/json/solarized_dark.json
edea_draw/themes/json/solarized_light.json
edea_draw/themes/json/wdark.json
edea_draw/themes/json/wlight.json
edea_draw-0.2.8.dist-info/METADATA
edea_draw-0.2.8.dist-info/WHEEL
edea_draw-0.2.8.dist-info/licenses/LICENSE.md
edea_draw-0.2.8.dist-info/RECORD
